<?xml version="1.0" encoding="UTF-8"?>

<!-- generated on 03/01/21 22:08:19 by Eclipse SUMO Version 1.2.0
<configuration xmlns:xsi="http://www.w3.org/2001/XMLSchema-instance" xsi:noNamespaceSchemaLocation="http://sumo.dlr.de/xsd/sumoConfiguration.xsd">

    <input>
        <net-file value="erlangen.net.xml"/>
        <route-files value="density_10vSpeed.rou.xml"/>
        <additional-files value="vtypes.add.xml"/>
    </input>

    <output>
        <vehroute-output value="density_10vSpeed_routes.xml"/>
    </output>

    <time>
        <begin value="0"/>
        <step-length value="0.1"/>
    </time>

    <report>
        <xml-validation value="never"/>
        <xml-validation.net value="never"/>
        <no-step-log value="true"/>
    </report>

    <gui_only>
        <start value="true"/>
        <tracker-interval value="0.1"/>
    </gui_only>

</configuration>
-->

<routes xmlns:xsi="http://www.w3.org/2001/XMLSchema-instance" xsi:noNamespaceSchemaLocation="http://sumo.dlr.de/xsd/routes_file.xsd">
    <vehicle id="vehicle_0" type="DEFAULT_VEHTYPE" depart="2.10" departSpeed="5.00" arrival="28.80">
        <route edges="-319929498#3 32038440#11"/>
    </vehicle>

    <vehicle id="vehicle_1" type="DEFAULT_VEHTYPE" depart="4.20" departSpeed="5.00" arrival="33.40">
        <route edges="-319929498#3 32038440#11"/>
    </vehicle>

    <vehicle id="vehicle_2" type="DEFAULT_VEHTYPE" depart="6.30" departSpeed="5.00" arrival="33.60">
        <route edges="-319929498#3 -319929498#2"/>
    </vehicle>

    <vehicle id="vehicle_3" type="DEFAULT_VEHTYPE" depart="8.40" departSpeed="5.00" arrival="35.10">
        <route edges="-319929498#3 -319929498#2"/>
    </vehicle>

    <vehicle id="vehicle_4" type="DEFAULT_VEHTYPE" depart="10.50" departSpeed="5.00" arrival="38.30">
        <route edges="-319929498#3 32038440#11"/>
    </vehicle>

    <vehicle id="vehicle_6" type="DEFAULT_VEHTYPE" depart="14.70" departSpeed="5.00" arrival="43.70">
        <route edges="-319929498#3 -319929498#2"/>
    </vehicle>

    <vehicle id="vehicle_5" type="DEFAULT_VEHTYPE" depart="12.60" departSpeed="5.00" arrival="44.90">
        <route edges="-319929498#3 32038440#11"/>
    </vehicle>

    <vehicle id="vehicle_7" type="DEFAULT_VEHTYPE" depart="16.80" departSpeed="5.00" arrival="48.30">
        <route edges="-319929498#3 32038440#11"/>
    </vehicle>

    <vehicle id="vehicle_8" type="DEFAULT_VEHTYPE" depart="18.90" departSpeed="5.00" arrival="50.20">
        <route edges="-319929498#3 32038440#11"/>
    </vehicle>

    <vehicle id="vehicle_10" type="DEFAULT_VEHTYPE" depart="23.10" departSpeed="5.00" arrival="52.10">
        <route edges="-319929498#3 -319929498#2"/>
    </vehicle>

    <vehicle id="vehicle_9" type="DEFAULT_VEHTYPE" depart="21.00" departSpeed="5.00" arrival="53.20">
        <route edges="-319929498#3 32038440#11"/>
    </vehicle>

    <vehicle id="vehicle_11" type="DEFAULT_VEHTYPE" depart="25.20" departSpeed="5.00" arrival="53.80">
        <route edges="-319929498#3 -319929498#2"/>
    </vehicle>

    <vehicle id="vehicle_12" type="DEFAULT_VEHTYPE" depart="27.30" departSpeed="5.00" arrival="56.70">
        <route edges="-319929498#3 32038440#11"/>
    </vehicle>

    <vehicle id="vehicle_13" type="DEFAULT_VEHTYPE" depart="29.40" departSpeed="5.00" arrival="57.10">
        <route edges="-319929498#3 -319929498#2"/>
    </vehicle>

    <vehicle id="vehicle_14" type="DEFAULT_VEHTYPE" depart="31.50" departSpeed="5.00" arrival="59.30">
        <route edges="-319929498#3 -319929498#2"/>
    </vehicle>

    <vehicle id="vehicle_15" type="DEFAULT_VEHTYPE" depart="33.60" departSpeed="5.00" arrival="61.50">
        <route edges="-319929498#3 -319929498#2"/>
    </vehicle>

    <vehicle id="vehicle_16" type="DEFAULT_VEHTYPE" depart="35.70" departSpeed="5.00" arrival="64.70">
        <route edges="-319929498#3 -319929498#2"/>
    </vehicle>

    <vehicle id="vehicle_17" type="DEFAULT_VEHTYPE" depart="37.80" departSpeed="5.00" arrival="67.50">
        <route edges="-319929498#3 32038440#11"/>
    </vehicle>

    <vehicle id="vehicle_19" type="DEFAULT_VEHTYPE" depart="42.00" departSpeed="5.00" arrival="69.20">
        <route edges="-319929498#3 -319929498#2"/>
    </vehicle>

    <vehicle id="vehicle_18" type="DEFAULT_VEHTYPE" depart="39.90" departSpeed="5.00" arrival="69.90">
        <route edges="-319929498#3 32038440#11"/>
    </vehicle>

    <vehicle id="vehicle_20" type="DEFAULT_VEHTYPE" depart="44.10" departSpeed="5.00" arrival="73.00">
        <route edges="-319929498#3 32038440#11"/>
    </vehicle>

    <vehicle id="vehicle_21" type="DEFAULT_VEHTYPE" depart="46.20" departSpeed="5.00" arrival="75.30">
        <route edges="-319929498#3 32038440#11"/>
    </vehicle>

    <vehicle id="vehicle_22" type="DEFAULT_VEHTYPE" depart="48.30" departSpeed="5.00" arrival="77.90">
        <route edges="-319929498#3 32038440#11"/>
    </vehicle>

    <vehicle id="vehicle_23" type="DEFAULT_VEHTYPE" depart="50.40" departSpeed="5.00" arrival="81.30">
        <route edges="-319929498#3 32038440#11"/>
    </vehicle>

    <vehicle id="vehicle_24" type="DEFAULT_VEHTYPE" depart="52.50" departSpeed="5.00" arrival="85.00">
        <route edges="-319929498#3 32038440#11"/>
    </vehicle>

    <vehicle id="vehicle_25" type="DEFAULT_VEHTYPE" depart="54.60" departSpeed="5.00" arrival="85.10">
        <route edges="-319929498#3 -319929498#2"/>
    </vehicle>

    <vehicle id="vehicle_26" type="DEFAULT_VEHTYPE" depart="56.70" departSpeed="5.00" arrival="86.70">
        <route edges="-319929498#3 -319929498#2"/>
    </vehicle>

    <vehicle id="vehicle_27" type="DEFAULT_VEHTYPE" depart="58.80" departSpeed="5.00" arrival="89.20">
        <route edges="-319929498#3 32038440#11"/>
    </vehicle>

    <vehicle id="vehicle_28" type="DEFAULT_VEHTYPE" depart="60.90" departSpeed="5.00" arrival="90.90">
        <route edges="-319929498#3 32038440#11"/>
    </vehicle>

    <vehicle id="vehicle_29" type="DEFAULT_VEHTYPE" depart="63.00" departSpeed="5.00" arrival="92.10">
        <route edges="-319929498#3 -319929498#2"/>
    </vehicle>

    <vehicle id="vehicle_30" type="DEFAULT_VEHTYPE" depart="65.10" departSpeed="5.00" arrival="93.60">
        <route edges="-319929498#3 -319929498#2"/>
    </vehicle>

    <vehicle id="vehicle_31" type="DEFAULT_VEHTYPE" depart="67.20" departSpeed="5.00" arrival="94.90">
        <route edges="-319929498#3 -319929498#2"/>
    </vehicle>

    <vehicle id="vehicle_33" type="DEFAULT_VEHTYPE" depart="71.40" departSpeed="5.00" arrival="97.70">
        <route edges="-319929498#3 -319929498#2"/>
    </vehicle>

    <vehicle id="vehicle_32" type="DEFAULT_VEHTYPE" depart="69.30" departSpeed="5.00" arrival="97.90">
        <route edges="-319929498#3 32038440#11"/>
    </vehicle>

    <vehicle id="vehicle_34" type="DEFAULT_VEHTYPE" depart="73.50" departSpeed="5.00" arrival="102.10">
        <route edges="-319929498#3 32038440#11"/>
    </vehicle>

    <vehicle id="vehicle_35" type="DEFAULT_VEHTYPE" depart="75.60" departSpeed="5.00" arrival="102.70">
        <route edges="-319929498#3 -319929498#2"/>
    </vehicle>

    <vehicle id="vehicle_36" type="DEFAULT_VEHTYPE" depart="77.70" departSpeed="5.00" arrival="106.50">
        <route edges="-319929498#3 32038440#11"/>
    </vehicle>

    <vehicle id="vehicle_37" type="DEFAULT_VEHTYPE" depart="79.80" departSpeed="5.00" arrival="108.20">
        <route edges="-319929498#3 32038440#11"/>
    </vehicle>

    <vehicle id="vehicle_38" type="DEFAULT_VEHTYPE" depart="81.90" departSpeed="5.00" arrival="108.60">
        <route edges="-319929498#3 -319929498#2"/>
    </vehicle>

    <vehicle id="vehicle_39" type="DEFAULT_VEHTYPE" depart="84.00" departSpeed="5.00" arrival="112.30">
        <route edges="-319929498#3 -319929498#2"/>
    </vehicle>

    <vehicle id="vehicle_40" type="DEFAULT_VEHTYPE" depart="86.10" departSpeed="5.00" arrival="113.80">
        <route edges="-319929498#3 -319929498#2"/>
    </vehicle>

    <vehicle id="vehicle_41" type="DEFAULT_VEHTYPE" depart="88.20" departSpeed="5.00" arrival="115.40">
        <route edges="-319929498#3 -319929498#2"/>
    </vehicle>

    <vehicle id="vehicle_42" type="DEFAULT_VEHTYPE" depart="90.30" departSpeed="5.00" arrival="116.80">
        <route edges="-319929498#3 -319929498#2"/>
    </vehicle>

    <vehicle id="vehicle_43" type="DEFAULT_VEHTYPE" depart="92.40" departSpeed="5.00" arrival="118.30">
        <route edges="-319929498#3 -319929498#2"/>
    </vehicle>

    <vehicle id="vehicle_44" type="DEFAULT_VEHTYPE" depart="94.50" departSpeed="5.00" arrival="121.50">
        <route edges="-319929498#3 32038440#11"/>
    </vehicle>

    <vehicle id="vehicle_45" type="DEFAULT_VEHTYPE" depart="96.60" departSpeed="5.00" arrival="122.10">
        <route edges="-319929498#3 -319929498#2"/>
    </vehicle>

    <vehicle id="vehicle_46" type="DEFAULT_VEHTYPE" depart="98.70" departSpeed="5.00" arrival="124.60">
        <route edges="-319929498#3 -319929498#2"/>
    </vehicle>

    <vehicle id="vehicle_47" type="DEFAULT_VEHTYPE" depart="100.80" departSpeed="5.00" arrival="129.10">
        <route edges="-319929498#3 -319929498#2"/>
    </vehicle>

    <vehicle id="vehicle_48" type="DEFAULT_VEHTYPE" depart="102.90" departSpeed="5.00" arrival="133.70">
        <route edges="-319929498#3 32038440#11"/>
    </vehicle>

    <vehicle id="vehicle_49" type="DEFAULT_VEHTYPE" depart="105.00" departSpeed="5.00" arrival="134.90">
        <route edges="-319929498#3 -319929498#2"/>
    </vehicle>

    <vehicle id="vehicle_51" type="DEFAULT_VEHTYPE" depart="109.20" departSpeed="5.00" arrival="137.20">
        <route edges="-319929498#3 -319929498#2"/>
    </vehicle>

    <vehicle id="vehicle_50" type="DEFAULT_VEHTYPE" depart="107.10" departSpeed="5.00" arrival="138.80">
        <route edges="-319929498#3 32038440#11"/>
    </vehicle>

    <vehicle id="vehicle_52" type="DEFAULT_VEHTYPE" depart="111.30" departSpeed="5.00" arrival="139.40">
        <route edges="-319929498#3 -319929498#2"/>
    </vehicle>

    <vehicle id="vehicle_53" type="DEFAULT_VEHTYPE" depart="113.40" departSpeed="5.00" arrival="142.00">
        <route edges="-319929498#3 32038440#11"/>
    </vehicle>

    <vehicle id="vehicle_54" type="DEFAULT_VEHTYPE" depart="115.50" departSpeed="5.00" arrival="143.50">
        <route edges="-319929498#3 -319929498#2"/>
    </vehicle>

    <vehicle id="vehicle_55" type="DEFAULT_VEHTYPE" depart="117.60" departSpeed="5.00" arrival="145.10">
        <route edges="-319929498#3 -319929498#2"/>
    </vehicle>

    <vehicle id="vehicle_56" type="DEFAULT_VEHTYPE" depart="119.70" departSpeed="5.00" arrival="148.00">
        <route edges="-319929498#3 -319929498#2"/>
    </vehicle>

    <vehicle id="vehicle_57" type="DEFAULT_VEHTYPE" depart="121.80" departSpeed="5.00" arrival="149.40">
        <route edges="-319929498#3 32038440#11"/>
    </vehicle>

    <vehicle id="vehicle_58" type="DEFAULT_VEHTYPE" depart="123.90" departSpeed="5.00" arrival="151.10">
        <route edges="-319929498#3 -319929498#2"/>
    </vehicle>

    <vehicle id="vehicle_59" type="DEFAULT_VEHTYPE" depart="126.00" departSpeed="5.00" arrival="153.10">
        <route edges="-319929498#3 -319929498#2"/>
    </vehicle>

    <vehicle id="vehicle_60" type="DEFAULT_VEHTYPE" depart="128.10" departSpeed="5.00" arrival="154.50">
        <route edges="-319929498#3 -319929498#2"/>
    </vehicle>

    <vehicle id="vehicle_61" type="DEFAULT_VEHTYPE" depart="130.20" departSpeed="5.00" arrival="155.90">
        <route edges="-319929498#3 -319929498#2"/>
    </vehicle>

    <vehicle id="vehicle_62" type="DEFAULT_VEHTYPE" depart="132.30" departSpeed="5.00" arrival="159.80">
        <route edges="-319929498#3 32038440#11"/>
    </vehicle>

    <vehicle id="vehicle_63" type="DEFAULT_VEHTYPE" depart="134.40" departSpeed="5.00" arrival="161.00">
        <route edges="-319929498#3 -319929498#2"/>
    </vehicle>

    <vehicle id="vehicle_64" type="DEFAULT_VEHTYPE" depart="136.50" departSpeed="5.00" arrival="165.80">
        <route edges="-319929498#3 32038440#11"/>
    </vehicle>

    <vehicle id="vehicle_65" type="DEFAULT_VEHTYPE" depart="138.60" departSpeed="5.00" arrival="169.40">
        <route edges="-319929498#3 32038440#11"/>
    </vehicle>

    <vehicle id="vehicle_66" type="DEFAULT_VEHTYPE" depart="140.70" departSpeed="5.00" arrival="171.40">
        <route edges="-319929498#3 32038440#11"/>
    </vehicle>

    <vehicle id="vehicle_68" type="DEFAULT_VEHTYPE" depart="144.90" departSpeed="5.00" arrival="173.40">
        <route edges="-319929498#3 -319929498#2"/>
    </vehicle>

    <vehicle id="vehicle_67" type="DEFAULT_VEHTYPE" depart="142.80" departSpeed="5.00" arrival="173.60">
        <route edges="-319929498#3 32038440#11"/>
    </vehicle>

    <vehicle id="vehicle_69" type="DEFAULT_VEHTYPE" depart="147.00" departSpeed="5.00" arrival="176.40">
        <route edges="-319929498#3 32038440#11"/>
    </vehicle>

    <vehicle id="vehicle_70" type="DEFAULT_VEHTYPE" depart="149.10" departSpeed="5.00" arrival="177.20">
        <route edges="-319929498#3 -319929498#2"/>
    </vehicle>

    <vehicle id="vehicle_71" type="DEFAULT_VEHTYPE" depart="151.20" departSpeed="5.00" arrival="180.80">
        <route edges="-319929498#3 32038440#11"/>
    </vehicle>

    <vehicle id="vehicle_72" type="DEFAULT_VEHTYPE" depart="153.30" departSpeed="5.00" arrival="181.80">
        <route edges="-319929498#3 -319929498#2"/>
    </vehicle>

    <vehicle id="vehicle_73" type="DEFAULT_VEHTYPE" depart="155.40" departSpeed="5.00" arrival="183.30">
        <route edges="-319929498#3 -319929498#2"/>
    </vehicle>

    <vehicle id="vehicle_74" type="DEFAULT_VEHTYPE" depart="157.50" departSpeed="5.00" arrival="185.00">
        <route edges="-319929498#3 -319929498#2"/>
    </vehicle>

    <vehicle id="vehicle_75" type="DEFAULT_VEHTYPE" depart="159.60" departSpeed="5.00" arrival="186.50">
        <route edges="-319929498#3 -319929498#2"/>
    </vehicle>

    <vehicle id="vehicle_76" type="DEFAULT_VEHTYPE" depart="161.70" departSpeed="5.00" arrival="189.30">
        <route edges="-319929498#3 32038440#11"/>
    </vehicle>

    <vehicle id="vehicle_77" type="DEFAULT_VEHTYPE" depart="163.80" departSpeed="5.00" arrival="190.60">
        <route edges="-319929498#3 -319929498#2"/>
    </vehicle>

    <vehicle id="vehicle_78" type="DEFAULT_VEHTYPE" depart="165.90" departSpeed="5.00" arrival="193.90">
        <route edges="-319929498#3 32038440#11"/>
    </vehicle>

    <vehicle id="vehicle_79" type="DEFAULT_VEHTYPE" depart="168.00" departSpeed="5.00" arrival="195.80">
        <route edges="-319929498#3 32038440#11"/>
    </vehicle>

    <vehicle id="vehicle_80" type="DEFAULT_VEHTYPE" depart="170.10" departSpeed="5.00" arrival="196.80">
        <route edges="-319929498#3 -319929498#2"/>
    </vehicle>

    <vehicle id="vehicle_81" type="DEFAULT_VEHTYPE" depart="172.20" departSpeed="5.00" arrival="200.50">
        <route edges="-319929498#3 32038440#11"/>
    </vehicle>

    <vehicle id="vehicle_82" type="DEFAULT_VEHTYPE" depart="174.30" departSpeed="5.00" arrival="201.20">
        <route edges="-319929498#3 -319929498#2"/>
    </vehicle>

    <vehicle id="vehicle_83" type="DEFAULT_VEHTYPE" depart="176.40" departSpeed="5.00" arrival="203.30">
        <route edges="-319929498#3 -319929498#2"/>
    </vehicle>

    <vehicle id="vehicle_84" type="DEFAULT_VEHTYPE" depart="178.50" departSpeed="5.00" arrival="204.70">
        <route edges="-319929498#3 -319929498#2"/>
    </vehicle>

    <vehicle id="vehicle_85" type="DEFAULT_VEHTYPE" depart="180.60" departSpeed="5.00" arrival="207.00">
        <route edges="-319929498#3 -319929498#2"/>
    </vehicle>

    <vehicle id="vehicle_86" type="DEFAULT_VEHTYPE" depart="182.70" departSpeed="5.00" arrival="210.40">
        <route edges="-319929498#3 32038440#11"/>
    </vehicle>

    <vehicle id="vehicle_87" type="DEFAULT_VEHTYPE" depart="184.80" departSpeed="5.00" arrival="210.90">
        <route edges="-319929498#3 -319929498#2"/>
    </vehicle>

    <vehicle id="vehicle_88" type="DEFAULT_VEHTYPE" depart="186.90" departSpeed="5.00" arrival="212.90">
        <route edges="-319929498#3 -319929498#2"/>
    </vehicle>

    <vehicle id="vehicle_89" type="DEFAULT_VEHTYPE" depart="189.00" departSpeed="5.00" arrival="216.40">
        <route edges="-319929498#3 32038440#11"/>
    </vehicle>

    <vehicle id="vehicle_90" type="DEFAULT_VEHTYPE" depart="191.10" departSpeed="5.00" arrival="217.30">
        <route edges="-319929498#3 -319929498#2"/>
    </vehicle>

    <vehicle id="vehicle_91" type="DEFAULT_VEHTYPE" depart="193.20" departSpeed="5.00" arrival="221.70">
        <route edges="-319929498#3 -319929498#2"/>
    </vehicle>

    <vehicle id="vehicle_93" type="DEFAULT_VEHTYPE" depart="197.40" departSpeed="5.00" arrival="227.30">
        <route edges="-319929498#3 -319929498#2"/>
    </vehicle>

    <vehicle id="vehicle_92" type="DEFAULT_VEHTYPE" depart="195.30" departSpeed="5.00" arrival="227.50">
        <route edges="-319929498#3 32038440#11"/>
    </vehicle>

    <vehicle id="vehicle_94" type="DEFAULT_VEHTYPE" depart="199.50" departSpeed="5.00" arrival="228.70">
        <route edges="-319929498#3 -319929498#2"/>
    </vehicle>

    <vehicle id="vehicle_95" type="DEFAULT_VEHTYPE" depart="201.60" departSpeed="5.00" arrival="230.70">
        <route edges="-319929498#3 32038440#11"/>
    </vehicle>

    <vehicle id="vehicle_96" type="DEFAULT_VEHTYPE" depart="203.70" departSpeed="5.00" arrival="233.30">
        <route edges="-319929498#3 32038440#11"/>
    </vehicle>

    <vehicle id="vehicle_97" type="DEFAULT_VEHTYPE" depart="205.80" departSpeed="5.00" arrival="236.70">
        <route edges="-319929498#3 32038440#11"/>
    </vehicle>

    <vehicle id="vehicle_99" type="DEFAULT_VEHTYPE" depart="210.00" departSpeed="5.00" arrival="238.20">
        <route edges="-319929498#3 -319929498#2"/>
    </vehicle>

    <vehicle id="vehicle_98" type="DEFAULT_VEHTYPE" depart="207.90" departSpeed="5.00" arrival="238.40">
        <route edges="-319929498#3 32038440#11"/>
    </vehicle>

    <vehicle id="vehicle_100" type="DEFAULT_VEHTYPE" depart="212.10" departSpeed="5.00" arrival="241.20">
        <route edges="-319929498#3 32038440#11"/>
    </vehicle>

    <vehicle id="vehicle_101" type="DEFAULT_VEHTYPE" depart="214.20" departSpeed="5.00" arrival="244.40">
        <route edges="-319929498#3 32038440#11"/>
    </vehicle>

    <vehicle id="vehicle_102" type="DEFAULT_VEHTYPE" depart="216.30" departSpeed="5.00" arrival="246.50">
        <route edges="-319929498#3 32038440#11"/>
    </vehicle>

    <vehicle id="vehicle_103" type="DEFAULT_VEHTYPE" depart="218.40" departSpeed="5.00" arrival="248.90">
        <route edges="-319929498#3 32038440#11"/>
    </vehicle>

    <vehicle id="vehicle_104" type="DEFAULT_VEHTYPE" depart="220.50" departSpeed="5.00" arrival="250.20">
        <route edges="-319929498#3 -319929498#2"/>
    </vehicle>

    <vehicle id="vehicle_105" type="DEFAULT_VEHTYPE" depart="222.60" departSpeed="5.00" arrival="251.60">
        <route edges="-319929498#3 -319929498#2"/>
    </vehicle>

    <vehicle id="vehicle_106" type="DEFAULT_VEHTYPE" depart="224.70" departSpeed="5.00" arrival="253.90">
        <route edges="-319929498#3 32038440#11"/>
    </vehicle>

    <vehicle id="vehicle_107" type="DEFAULT_VEHTYPE" depart="226.80" departSpeed="5.00" arrival="254.50">
        <route edges="-319929498#3 -319929498#2"/>
    </vehicle>

    <vehicle id="vehicle_108" type="DEFAULT_VEHTYPE" depart="228.90" departSpeed="5.00" arrival="257.30">
        <route edges="-319929498#3 32038440#11"/>
    </vehicle>

    <vehicle id="vehicle_109" type="DEFAULT_VEHTYPE" depart="231.00" departSpeed="5.00" arrival="260.60">
        <route edges="-319929498#3 32038440#11"/>
    </vehicle>

    <vehicle id="vehicle_110" type="DEFAULT_VEHTYPE" depart="233.10" departSpeed="5.00" arrival="263.30">
        <route edges="-319929498#3 32038440#11"/>
    </vehicle>

    <vehicle id="vehicle_111" type="DEFAULT_VEHTYPE" depart="235.20" departSpeed="5.00" arrival="264.80">
        <route edges="-319929498#3 -319929498#2"/>
    </vehicle>

    <vehicle id="vehicle_112" type="DEFAULT_VEHTYPE" depart="237.30" departSpeed="5.00" arrival="266.00">
        <route edges="-319929498#3 32038440#11"/>
    </vehicle>

    <vehicle id="vehicle_113" type="DEFAULT_VEHTYPE" depart="239.40" departSpeed="5.00" arrival="268.90">
        <route edges="-319929498#3 32038440#11"/>
    </vehicle>

    <vehicle id="vehicle_114" type="DEFAULT_VEHTYPE" depart="241.50" departSpeed="5.00" arrival="270.70">
        <route edges="-319929498#3 32038440#11"/>
    </vehicle>

    <vehicle id="vehicle_116" type="DEFAULT_VEHTYPE" depart="245.70" departSpeed="5.00" arrival="273.20">
        <route edges="-319929498#3 -319929498#2"/>
    </vehicle>

    <vehicle id="vehicle_115" type="DEFAULT_VEHTYPE" depart="243.60" departSpeed="5.00" arrival="274.20">
        <route edges="-319929498#3 32038440#11"/>
    </vehicle>

    <vehicle id="vehicle_117" type="DEFAULT_VEHTYPE" depart="247.80" departSpeed="5.00" arrival="275.60">
        <route edges="-319929498#3 -319929498#2"/>
    </vehicle>

    <vehicle id="vehicle_118" type="DEFAULT_VEHTYPE" depart="249.90" departSpeed="5.00" arrival="279.10">
        <route edges="-319929498#3 32038440#11"/>
    </vehicle>

    <vehicle id="vehicle_119" type="DEFAULT_VEHTYPE" depart="252.00" departSpeed="5.00" arrival="280.90">
        <route edges="-319929498#3 32038440#11"/>
    </vehicle>

    <vehicle id="vehicle_120" type="DEFAULT_VEHTYPE" depart="254.10" departSpeed="5.00" arrival="282.50">
        <route edges="-319929498#3 -319929498#2"/>
    </vehicle>

    <vehicle id="vehicle_121" type="DEFAULT_VEHTYPE" depart="256.20" departSpeed="5.00" arrival="283.90">
        <route edges="-319929498#3 -319929498#2"/>
    </vehicle>

    <vehicle id="vehicle_122" type="DEFAULT_VEHTYPE" depart="258.30" departSpeed="5.00" arrival="285.40">
        <route edges="-319929498#3 -319929498#2"/>
    </vehicle>

    <vehicle id="vehicle_123" type="DEFAULT_VEHTYPE" depart="260.40" departSpeed="5.00" arrival="286.90">
        <route edges="-319929498#3 -319929498#2"/>
    </vehicle>

    <vehicle id="vehicle_124" type="DEFAULT_VEHTYPE" depart="262.50" departSpeed="5.00" arrival="289.70">
        <route edges="-319929498#3 32038440#11"/>
    </vehicle>

    <vehicle id="vehicle_125" type="DEFAULT_VEHTYPE" depart="264.60" departSpeed="5.00" arrival="291.50">
        <route edges="-319929498#3 32038440#11"/>
    </vehicle>

    <vehicle id="vehicle_126" type="DEFAULT_VEHTYPE" depart="266.70" departSpeed="5.00" arrival="294.70">
        <route edges="-319929498#3 32038440#11"/>
    </vehicle>

    <vehicle id="vehicle_127" type="DEFAULT_VEHTYPE" depart="268.80" departSpeed="5.00" arrival="301.40">
        <route edges="-319929498#3 32038440#11"/>
    </vehicle>

    <vehicle id="vehicle_128" type="DEFAULT_VEHTYPE" depart="270.90" departSpeed="5.00" arrival="303.10">
        <route edges="-319929498#3 32038440#11"/>
    </vehicle>

    <vehicle id="vehicle_129" type="DEFAULT_VEHTYPE" depart="273.00" departSpeed="5.00" arrival="305.00">
        <route edges="-319929498#3 32038440#11"/>
    </vehicle>

    <vehicle id="vehicle_130" type="DEFAULT_VEHTYPE" depart="275.10" departSpeed="5.00" arrival="306.80">
        <route edges="-319929498#3 32038440#11"/>
    </vehicle>

    <vehicle id="vehicle_131" type="DEFAULT_VEHTYPE" depart="277.20" departSpeed="5.00" arrival="308.60">
        <route edges="-319929498#3 32038440#11"/>
    </vehicle>

    <vehicle id="vehicle_132" type="DEFAULT_VEHTYPE" depart="279.30" departSpeed="5.00" arrival="309.30">
        <route edges="-319929498#3 -319929498#2"/>
    </vehicle>

    <vehicle id="vehicle_134" type="DEFAULT_VEHTYPE" depart="283.50" departSpeed="5.00" arrival="311.40">
        <route edges="-319929498#3 -319929498#2"/>
    </vehicle>

    <vehicle id="vehicle_133" type="DEFAULT_VEHTYPE" depart="281.40" departSpeed="5.00" arrival="311.60">
        <route edges="-319929498#3 32038440#11"/>
    </vehicle>

    <vehicle id="vehicle_135" type="DEFAULT_VEHTYPE" depart="285.60" departSpeed="5.00" arrival="313.90">
        <route edges="-319929498#3 -319929498#2"/>
    </vehicle>

    <vehicle id="vehicle_136" type="DEFAULT_VEHTYPE" depart="287.70" departSpeed="5.00" arrival="316.30">
        <route edges="-319929498#3 32038440#11"/>
    </vehicle>

    <vehicle id="vehicle_137" type="DEFAULT_VEHTYPE" depart="289.80" departSpeed="5.00" arrival="319.40">
        <route edges="-319929498#3 32038440#11"/>
    </vehicle>

    <vehicle id="vehicle_138" type="DEFAULT_VEHTYPE" depart="291.90" departSpeed="5.00" arrival="321.60">
        <route edges="-319929498#3 32038440#11"/>
    </vehicle>

    <vehicle id="vehicle_139" type="DEFAULT_VEHTYPE" depart="294.00" departSpeed="5.00" arrival="322.80">
        <route edges="-319929498#3 -319929498#2"/>
    </vehicle>

    <vehicle id="vehicle_140" type="DEFAULT_VEHTYPE" depart="296.10" departSpeed="5.00" arrival="324.20">
        <route edges="-319929498#3 -319929498#2"/>
    </vehicle>

    <vehicle id="vehicle_141" type="DEFAULT_VEHTYPE" depart="298.20" departSpeed="5.00" arrival="325.80">
        <route edges="-319929498#3 32038440#11"/>
    </vehicle>

    <vehicle id="vehicle_142" type="DEFAULT_VEHTYPE" depart="300.30" departSpeed="5.00" arrival="328.40">
        <route edges="-319929498#3 -319929498#2"/>
    </vehicle>

    <vehicle id="vehicle_143" type="DEFAULT_VEHTYPE" depart="302.40" departSpeed="5.00" arrival="330.10">
        <route edges="-319929498#3 32038440#11"/>
    </vehicle>

    <vehicle id="vehicle_144" type="DEFAULT_VEHTYPE" depart="304.50" departSpeed="5.00" arrival="340.50">
        <route edges="-319929498#3 32038440#11"/>
    </vehicle>

    <vehicle id="vehicle_145" type="DEFAULT_VEHTYPE" depart="306.60" departSpeed="5.00" arrival="342.30">
        <route edges="-319929498#3 32038440#11"/>
    </vehicle>

    <vehicle id="vehicle_147" type="DEFAULT_VEHTYPE" depart="310.80" departSpeed="5.00" arrival="342.80">
        <route edges="-319929498#3 -319929498#2"/>
    </vehicle>

    <vehicle id="vehicle_146" type="DEFAULT_VEHTYPE" depart="308.70" departSpeed="5.00" arrival="344.40">
        <route edges="-319929498#3 32038440#11"/>
    </vehicle>

    <vehicle id="vehicle_148" type="DEFAULT_VEHTYPE" depart="312.90" departSpeed="5.00" arrival="344.40">
        <route edges="-319929498#3 -319929498#2"/>
    </vehicle>

    <vehicle id="vehicle_149" type="DEFAULT_VEHTYPE" depart="315.00" departSpeed="5.00" arrival="345.90">
        <route edges="-319929498#3 -319929498#2"/>
    </vehicle>

    <vehicle id="vehicle_150" type="DEFAULT_VEHTYPE" depart="317.10" departSpeed="5.00" arrival="349.10">
        <route edges="-319929498#3 32038440#11"/>
    </vehicle>

    <vehicle id="vehicle_151" type="DEFAULT_VEHTYPE" depart="319.20" departSpeed="5.00" arrival="351.00">
        <route edges="-319929498#3 32038440#11"/>
    </vehicle>

    <vehicle id="vehicle_152" type="DEFAULT_VEHTYPE" depart="321.30" departSpeed="5.00" arrival="351.20">
        <route edges="-319929498#3 -319929498#2"/>
    </vehicle>

    <vehicle id="vehicle_153" type="DEFAULT_VEHTYPE" depart="323.40" departSpeed="5.00" arrival="355.40">
        <route edges="-319929498#3 32038440#11"/>
    </vehicle>

    <vehicle id="vehicle_154" type="DEFAULT_VEHTYPE" depart="325.50" departSpeed="5.00" arrival="357.20">
        <route edges="-319929498#3 32038440#11"/>
    </vehicle>

    <vehicle id="vehicle_155" type="DEFAULT_VEHTYPE" depart="327.60" departSpeed="5.00" arrival="358.90">
        <route edges="-319929498#3 32038440#11"/>
    </vehicle>

    <vehicle id="vehicle_156" type="DEFAULT_VEHTYPE" depart="329.70" departSpeed="5.00" arrival="360.60">
        <route edges="-319929498#3 32038440#11"/>
    </vehicle>

    <vehicle id="vehicle_157" type="DEFAULT_VEHTYPE" depart="331.80" departSpeed="5.00" arrival="362.60">
        <route edges="-319929498#3 32038440#11"/>
    </vehicle>

    <vehicle id="vehicle_158" type="DEFAULT_VEHTYPE" depart="333.90" departSpeed="5.00" arrival="364.50">
        <route edges="-319929498#3 -319929498#2"/>
    </vehicle>

    <vehicle id="vehicle_159" type="DEFAULT_VEHTYPE" depart="336.00" departSpeed="5.00" arrival="365.50">
        <route edges="-319929498#3 32038440#11"/>
    </vehicle>

    <vehicle id="vehicle_160" type="DEFAULT_VEHTYPE" depart="338.10" departSpeed="5.00" arrival="370.20">
        <route edges="-319929498#3 32038440#11"/>
    </vehicle>

    <vehicle id="vehicle_161" type="DEFAULT_VEHTYPE" depart="340.20" departSpeed="5.00" arrival="371.90">
        <route edges="-319929498#3 32038440#11"/>
    </vehicle>

    <vehicle id="vehicle_162" type="DEFAULT_VEHTYPE" depart="342.30" departSpeed="5.00" arrival="373.90">
        <route edges="-319929498#3 32038440#11"/>
    </vehicle>

    <vehicle id="vehicle_163" type="DEFAULT_VEHTYPE" depart="344.40" departSpeed="5.00" arrival="375.60">
        <route edges="-319929498#3 32038440#11"/>
    </vehicle>

    <vehicle id="vehicle_164" type="DEFAULT_VEHTYPE" depart="346.50" departSpeed="5.00" arrival="377.50">
        <route edges="-319929498#3 32038440#11"/>
    </vehicle>

    <vehicle id="vehicle_165" type="DEFAULT_VEHTYPE" depart="348.60" departSpeed="5.00" arrival="378.90">
        <route edges="-319929498#3 -319929498#2"/>
    </vehicle>

    <vehicle id="vehicle_166" type="DEFAULT_VEHTYPE" depart="350.70" departSpeed="5.00" arrival="381.20">
        <route edges="-319929498#3 32038440#11"/>
    </vehicle>

    <vehicle id="vehicle_167" type="DEFAULT_VEHTYPE" depart="352.80" departSpeed="5.00" arrival="383.10">
        <route edges="-319929498#3 32038440#11"/>
    </vehicle>

    <vehicle id="vehicle_168" type="DEFAULT_VEHTYPE" depart="354.90" departSpeed="5.00" arrival="385.60">
        <route edges="-319929498#3 32038440#11"/>
    </vehicle>

    <vehicle id="vehicle_170" type="DEFAULT_VEHTYPE" depart="359.10" departSpeed="5.00" arrival="387.90">
        <route edges="-319929498#3 -319929498#2"/>
    </vehicle>

    <vehicle id="vehicle_169" type="DEFAULT_VEHTYPE" depart="357.00" departSpeed="5.00" arrival="388.10">
        <route edges="-319929498#3 32038440#11"/>
    </vehicle>

    <vehicle id="vehicle_171" type="DEFAULT_VEHTYPE" depart="361.20" departSpeed="5.00" arrival="392.60">
        <route edges="-319929498#3 32038440#11"/>
    </vehicle>

    <vehicle id="vehicle_172" type="DEFAULT_VEHTYPE" depart="363.30" departSpeed="5.00" arrival="393.30">
        <route edges="-319929498#3 -319929498#2"/>
    </vehicle>

    <vehicle id="vehicle_173" type="DEFAULT_VEHTYPE" depart="365.40" departSpeed="5.00" arrival="394.80">
        <route edges="-319929498#3 -319929498#2"/>
    </vehicle>

    <vehicle id="vehicle_174" type="DEFAULT_VEHTYPE" depart="367.50" departSpeed="5.00" arrival="396.40">
        <route edges="-319929498#3 -319929498#2"/>
    </vehicle>

    <vehicle id="vehicle_175" type="DEFAULT_VEHTYPE" depart="369.60" departSpeed="5.00" arrival="398.00">
        <route edges="-319929498#3 -319929498#2"/>
    </vehicle>

    <vehicle id="vehicle_176" type="DEFAULT_VEHTYPE" depart="371.70" departSpeed="5.00" arrival="399.50">
        <route edges="-319929498#3 -319929498#2"/>
    </vehicle>

    <vehicle id="vehicle_177" type="DEFAULT_VEHTYPE" depart="373.80" departSpeed="5.00" arrival="401.00">
        <route edges="-319929498#3 -319929498#2"/>
    </vehicle>

    <vehicle id="vehicle_178" type="DEFAULT_VEHTYPE" depart="375.90" departSpeed="5.00" arrival="402.40">
        <route edges="-319929498#3 -319929498#2"/>
    </vehicle>

    <vehicle id="vehicle_179" type="DEFAULT_VEHTYPE" depart="378.00" departSpeed="5.00" arrival="403.90">
        <route edges="-319929498#3 -319929498#2"/>
    </vehicle>

    <vehicle id="vehicle_180" type="DEFAULT_VEHTYPE" depart="380.10" departSpeed="5.00" arrival="405.30">
        <route edges="-319929498#3 -319929498#2"/>
    </vehicle>

    <vehicle id="vehicle_181" type="DEFAULT_VEHTYPE" depart="382.20" departSpeed="5.00" arrival="407.60">
        <route edges="-319929498#3 -319929498#2"/>
    </vehicle>

    <vehicle id="vehicle_182" type="DEFAULT_VEHTYPE" depart="384.30" departSpeed="5.00" arrival="409.50">
        <route edges="-319929498#3 -319929498#2"/>
    </vehicle>

    <vehicle id="vehicle_183" type="DEFAULT_VEHTYPE" depart="386.40" departSpeed="5.00" arrival="411.00">
        <route edges="-319929498#3 -319929498#2"/>
    </vehicle>

    <vehicle id="vehicle_184" type="DEFAULT_VEHTYPE" depart="388.50" departSpeed="5.00" arrival="415.70">
        <route edges="-319929498#3 -319929498#2"/>
    </vehicle>

    <vehicle id="vehicle_185" type="DEFAULT_VEHTYPE" depart="390.60" departSpeed="5.00" arrival="420.40">
        <route edges="-319929498#3 32038440#11"/>
    </vehicle>

    <vehicle id="vehicle_186" type="DEFAULT_VEHTYPE" depart="392.70" departSpeed="5.00" arrival="422.20">
        <route edges="-319929498#3 32038440#11"/>
    </vehicle>

    <vehicle id="vehicle_187" type="DEFAULT_VEHTYPE" depart="394.80" departSpeed="5.00" arrival="423.70">
        <route edges="-319929498#3 -319929498#2"/>
    </vehicle>

    <vehicle id="vehicle_188" type="DEFAULT_VEHTYPE" depart="396.90" departSpeed="5.00" arrival="425.20">
        <route edges="-319929498#3 -319929498#2"/>
    </vehicle>

    <vehicle id="vehicle_189" type="DEFAULT_VEHTYPE" depart="399.00" departSpeed="5.00" arrival="426.70">
        <route edges="-319929498#3 -319929498#2"/>
    </vehicle>

    <vehicle id="vehicle_190" type="DEFAULT_VEHTYPE" depart="401.10" departSpeed="5.00" arrival="429.30">
        <route edges="-319929498#3 -319929498#2"/>
    </vehicle>

    <vehicle id="vehicle_191" type="DEFAULT_VEHTYPE" depart="403.20" departSpeed="5.00" arrival="432.70">
        <route edges="-319929498#3 32038440#11"/>
    </vehicle>

    <vehicle id="vehicle_192" type="DEFAULT_VEHTYPE" depart="405.30" departSpeed="5.00" arrival="434.50">
        <route edges="-319929498#3 32038440#11"/>
    </vehicle>

    <vehicle id="vehicle_193" type="DEFAULT_VEHTYPE" depart="407.40" departSpeed="5.00" arrival="436.30">
        <route edges="-319929498#3 32038440#11"/>
    </vehicle>

    <vehicle id="vehicle_194" type="DEFAULT_VEHTYPE" depart="409.50" departSpeed="5.00" arrival="438.60">
        <route edges="-319929498#3 32038440#11"/>
    </vehicle>

    <vehicle id="vehicle_195" type="DEFAULT_VEHTYPE" depart="411.60" departSpeed="5.00" arrival="441.60">
        <route edges="-319929498#3 -319929498#2"/>
    </vehicle>

    <vehicle id="vehicle_196" type="DEFAULT_VEHTYPE" depart="413.70" departSpeed="5.00" arrival="443.10">
        <route edges="-319929498#3 -319929498#2"/>
    </vehicle>

    <vehicle id="vehicle_198" type="DEFAULT_VEHTYPE" depart="417.90" departSpeed="5.00" arrival="445.90">
        <route edges="-319929498#3 -319929498#2"/>
    </vehicle>

    <vehicle id="vehicle_197" type="DEFAULT_VEHTYPE" depart="415.80" departSpeed="5.00" arrival="446.80">
        <route edges="-319929498#3 32038440#11"/>
    </vehicle>

    <vehicle id="vehicle_199" type="DEFAULT_VEHTYPE" depart="420.00" departSpeed="5.00" arrival="450.40">
        <route edges="-319929498#3 -319929498#2"/>
    </vehicle>

    <vehicle id="vehicle_200" type="DEFAULT_VEHTYPE" depart="422.10" departSpeed="5.00" arrival="451.90">
        <route edges="-319929498#3 -319929498#2"/>
    </vehicle>

    <vehicle id="vehicle_201" type="DEFAULT_VEHTYPE" depart="424.20" departSpeed="5.00" arrival="455.20">
        <route edges="-319929498#3 32038440#11"/>
    </vehicle>

    <vehicle id="vehicle_203" type="DEFAULT_VEHTYPE" depart="428.40" departSpeed="5.00" arrival="456.40">
        <route edges="-319929498#3 -319929498#2"/>
    </vehicle>

    <vehicle id="vehicle_202" type="DEFAULT_VEHTYPE" depart="426.30" departSpeed="5.00" arrival="457.00">
        <route edges="-319929498#3 32038440#11"/>
    </vehicle>

    <vehicle id="vehicle_204" type="DEFAULT_VEHTYPE" depart="430.50" departSpeed="5.00" arrival="459.40">
        <route edges="-319929498#3 32038440#11"/>
    </vehicle>

    <vehicle id="vehicle_205" type="DEFAULT_VEHTYPE" depart="432.60" departSpeed="5.00" arrival="460.60">
        <route edges="-319929498#3 -319929498#2"/>
    </vehicle>

    <vehicle id="vehicle_206" type="DEFAULT_VEHTYPE" depart="434.70" departSpeed="5.00" arrival="462.20">
        <route edges="-319929498#3 -319929498#2"/>
    </vehicle>

    <vehicle id="vehicle_207" type="DEFAULT_VEHTYPE" depart="436.80" departSpeed="5.00" arrival="463.90">
        <route edges="-319929498#3 -319929498#2"/>
    </vehicle>

    <vehicle id="vehicle_208" type="DEFAULT_VEHTYPE" depart="438.90" departSpeed="5.00" arrival="467.70">
        <route edges="-319929498#3 32038440#11"/>
    </vehicle>

    <vehicle id="vehicle_209" type="DEFAULT_VEHTYPE" depart="441.00" departSpeed="5.00" arrival="469.80">
        <route edges="-319929498#3 32038440#11"/>
    </vehicle>

    <vehicle id="vehicle_210" type="DEFAULT_VEHTYPE" depart="443.10" departSpeed="5.00" arrival="471.50">
        <route edges="-319929498#3 32038440#11"/>
    </vehicle>

    <vehicle id="vehicle_211" type="DEFAULT_VEHTYPE" depart="445.20" departSpeed="5.00" arrival="472.30">
        <route edges="-319929498#3 -319929498#2"/>
    </vehicle>

    <vehicle id="vehicle_212" type="DEFAULT_VEHTYPE" depart="447.30" departSpeed="5.00" arrival="475.90">
        <route edges="-319929498#3 32038440#11"/>
    </vehicle>

    <vehicle id="vehicle_213" type="DEFAULT_VEHTYPE" depart="449.40" departSpeed="5.00" arrival="476.00">
        <route edges="-319929498#3 -319929498#2"/>
    </vehicle>

    <vehicle id="vehicle_214" type="DEFAULT_VEHTYPE" depart="451.50" departSpeed="5.00" arrival="481.80">
        <route edges="-319929498#3 -319929498#2"/>
    </vehicle>

    <vehicle id="vehicle_215" type="DEFAULT_VEHTYPE" depart="453.60" departSpeed="5.00" arrival="482.70">
        <route edges="-319929498#3 32038440#11"/>
    </vehicle>

    <vehicle id="vehicle_216" type="DEFAULT_VEHTYPE" depart="455.70" departSpeed="5.00" arrival="485.90">
        <route edges="-319929498#3 32038440#11"/>
    </vehicle>

    <vehicle id="vehicle_217" type="DEFAULT_VEHTYPE" depart="457.80" departSpeed="5.00" arrival="486.00">
        <route edges="-319929498#3 -319929498#2"/>
    </vehicle>

    <vehicle id="vehicle_218" type="DEFAULT_VEHTYPE" depart="459.90" departSpeed="5.00" arrival="488.90">
        <route edges="-319929498#3 32038440#11"/>
    </vehicle>

    <vehicle id="vehicle_219" type="DEFAULT_VEHTYPE" depart="462.00" departSpeed="5.00" arrival="492.80">
        <route edges="-319929498#3 32038440#11"/>
    </vehicle>

    <vehicle id="vehicle_221" type="DEFAULT_VEHTYPE" depart="466.20" departSpeed="5.00" arrival="494.10">
        <route edges="-319929498#3 -319929498#2"/>
    </vehicle>

    <vehicle id="vehicle_220" type="DEFAULT_VEHTYPE" depart="464.10" departSpeed="5.00" arrival="494.60">
        <route edges="-319929498#3 32038440#11"/>
    </vehicle>

    <vehicle id="vehicle_222" type="DEFAULT_VEHTYPE" depart="468.30" departSpeed="5.00" arrival="498.50">
        <route edges="-319929498#3 -319929498#2"/>
    </vehicle>

    <vehicle id="vehicle_223" type="DEFAULT_VEHTYPE" depart="470.40" departSpeed="5.00" arrival="500.00">
        <route edges="-319929498#3 -319929498#2"/>
    </vehicle>

    <vehicle id="vehicle_224" type="DEFAULT_VEHTYPE" depart="472.50" departSpeed="5.00" arrival="501.40">
        <route edges="-319929498#3 -319929498#2"/>
    </vehicle>

    <vehicle id="vehicle_225" type="DEFAULT_VEHTYPE" depart="474.60" departSpeed="5.00" arrival="503.90">
        <route edges="-319929498#3 32038440#11"/>
    </vehicle>

    <vehicle id="vehicle_226" type="DEFAULT_VEHTYPE" depart="476.70" departSpeed="5.00" arrival="505.60">
        <route edges="-319929498#3 32038440#11"/>
    </vehicle>

    <vehicle id="vehicle_227" type="DEFAULT_VEHTYPE" depart="478.80" departSpeed="5.00" arrival="507.40">
        <route edges="-319929498#3 32038440#11"/>
    </vehicle>

    <vehicle id="vehicle_228" type="DEFAULT_VEHTYPE" depart="480.90" departSpeed="5.00" arrival="508.20">
        <route edges="-319929498#3 -319929498#2"/>
    </vehicle>

    <vehicle id="vehicle_229" type="DEFAULT_VEHTYPE" depart="483.00" departSpeed="5.00" arrival="510.30">
        <route edges="-319929498#3 -319929498#2"/>
    </vehicle>

    <vehicle id="vehicle_230" type="DEFAULT_VEHTYPE" depart="485.10" departSpeed="5.00" arrival="513.20">
        <route edges="-319929498#3 32038440#11"/>
    </vehicle>

    <vehicle id="vehicle_231" type="DEFAULT_VEHTYPE" depart="487.20" departSpeed="5.00" arrival="513.50">
        <route edges="-319929498#3 -319929498#2"/>
    </vehicle>

    <vehicle id="vehicle_232" type="DEFAULT_VEHTYPE" depart="489.30" departSpeed="5.00" arrival="518.10">
        <route edges="-319929498#3 32038440#11"/>
    </vehicle>

    <vehicle id="vehicle_233" type="DEFAULT_VEHTYPE" depart="491.40" departSpeed="5.00" arrival="519.90">
        <route edges="-319929498#3 32038440#11"/>
    </vehicle>

    <vehicle id="vehicle_234" type="DEFAULT_VEHTYPE" depart="493.50" departSpeed="5.00" arrival="523.70">
        <route edges="-319929498#3 32038440#11"/>
    </vehicle>

    <vehicle id="vehicle_235" type="DEFAULT_VEHTYPE" depart="495.60" departSpeed="5.00" arrival="524.00">
        <route edges="-319929498#3 -319929498#2"/>
    </vehicle>

    <vehicle id="vehicle_236" type="DEFAULT_VEHTYPE" depart="497.70" departSpeed="5.00" arrival="526.40">
        <route edges="-319929498#3 32038440#11"/>
    </vehicle>

    <vehicle id="vehicle_237" type="DEFAULT_VEHTYPE" depart="499.80" departSpeed="5.00" arrival="530.70">
        <route edges="-319929498#3 32038440#11"/>
    </vehicle>

    <vehicle id="vehicle_239" type="DEFAULT_VEHTYPE" depart="504.00" departSpeed="5.00" arrival="531.80">
        <route edges="-319929498#3 -319929498#2"/>
    </vehicle>

    <vehicle id="vehicle_238" type="DEFAULT_VEHTYPE" depart="501.90" departSpeed="5.00" arrival="532.40">
        <route edges="-319929498#3 32038440#11"/>
    </vehicle>

    <vehicle id="vehicle_240" type="DEFAULT_VEHTYPE" depart="506.10" departSpeed="5.00" arrival="536.20">
        <route edges="-319929498#3 32038440#11"/>
    </vehicle>

    <vehicle id="vehicle_241" type="DEFAULT_VEHTYPE" depart="508.20" departSpeed="5.00" arrival="538.10">
        <route edges="-319929498#3 32038440#11"/>
    </vehicle>

    <vehicle id="vehicle_242" type="DEFAULT_VEHTYPE" depart="510.30" departSpeed="5.00" arrival="538.90">
        <route edges="-319929498#3 -319929498#2"/>
    </vehicle>

    <vehicle id="vehicle_243" type="DEFAULT_VEHTYPE" depart="512.40" departSpeed="5.00" arrival="540.40">
        <route edges="-319929498#3 -319929498#2"/>
    </vehicle>

    <vehicle id="vehicle_244" type="DEFAULT_VEHTYPE" depart="514.50" departSpeed="5.00" arrival="541.90">
        <route edges="-319929498#3 -319929498#2"/>
    </vehicle>

    <vehicle id="vehicle_245" type="DEFAULT_VEHTYPE" depart="516.60" departSpeed="5.00" arrival="543.50">
        <route edges="-319929498#3 -319929498#2"/>
    </vehicle>

    <vehicle id="vehicle_246" type="DEFAULT_VEHTYPE" depart="518.70" departSpeed="5.00" arrival="545.30">
        <route edges="-319929498#3 -319929498#2"/>
    </vehicle>

    <vehicle id="vehicle_247" type="DEFAULT_VEHTYPE" depart="520.80" departSpeed="5.00" arrival="546.80">
        <route edges="-319929498#3 -319929498#2"/>
    </vehicle>

    <vehicle id="vehicle_248" type="DEFAULT_VEHTYPE" depart="522.90" departSpeed="5.00" arrival="549.10">
        <route edges="-319929498#3 32038440#11"/>
    </vehicle>

    <vehicle id="vehicle_249" type="DEFAULT_VEHTYPE" depart="525.00" departSpeed="5.00" arrival="550.30">
        <route edges="-319929498#3 -319929498#2"/>
    </vehicle>

    <vehicle id="vehicle_250" type="DEFAULT_VEHTYPE" depart="527.10" departSpeed="5.00" arrival="554.50">
        <route edges="-319929498#3 -319929498#2"/>
    </vehicle>

    <vehicle id="vehicle_252" type="DEFAULT_VEHTYPE" depart="531.30" departSpeed="5.00" arrival="559.70">
        <route edges="-319929498#3 -319929498#2"/>
    </vehicle>

    <vehicle id="vehicle_251" type="DEFAULT_VEHTYPE" depart="529.20" departSpeed="5.00" arrival="560.00">
        <route edges="-319929498#3 32038440#11"/>
    </vehicle>

    <vehicle id="vehicle_253" type="DEFAULT_VEHTYPE" depart="533.40" departSpeed="5.00" arrival="562.90">
        <route edges="-319929498#3 32038440#11"/>
    </vehicle>

    <vehicle id="vehicle_254" type="DEFAULT_VEHTYPE" depart="535.50" departSpeed="5.00" arrival="566.60">
        <route edges="-319929498#3 32038440#11"/>
    </vehicle>

    <vehicle id="vehicle_256" type="DEFAULT_VEHTYPE" depart="539.70" departSpeed="5.00" arrival="572.30">
        <route edges="-319929498#3 -319929498#2"/>
    </vehicle>

    <vehicle id="vehicle_257" type="DEFAULT_VEHTYPE" depart="541.80" departSpeed="5.00" arrival="573.80">
        <route edges="-319929498#3 -319929498#2"/>
    </vehicle>

    <vehicle id="vehicle_255" type="DEFAULT_VEHTYPE" depart="537.60" departSpeed="5.00" arrival="574.80">
        <route edges="-319929498#3 32038440#11"/>
    </vehicle>

    <vehicle id="vehicle_258" type="DEFAULT_VEHTYPE" depart="543.90" departSpeed="5.00" arrival="576.70">
        <route edges="-319929498#3 32038440#11"/>
    </vehicle>

    <vehicle id="vehicle_259" type="DEFAULT_VEHTYPE" depart="546.00" departSpeed="5.00" arrival="580.50">
        <route edges="-319929498#3 32038440#11"/>
    </vehicle>

    <vehicle id="vehicle_261" type="DEFAULT_VEHTYPE" depart="550.20" departSpeed="5.00" arrival="581.50">
        <route edges="-319929498#3 -319929498#2"/>
    </vehicle>

    <vehicle id="vehicle_262" type="DEFAULT_VEHTYPE" depart="552.30" departSpeed="5.00" arrival="583.20">
        <route edges="-319929498#3 -319929498#2"/>
    </vehicle>

    <vehicle id="vehicle_260" type="DEFAULT_VEHTYPE" depart="548.10" departSpeed="5.00" arrival="584.10">
        <route edges="-319929498#3 32038440#11"/>
    </vehicle>

    <vehicle id="vehicle_263" type="DEFAULT_VEHTYPE" depart="554.40" departSpeed="5.00" arrival="586.90">
        <route edges="-319929498#3 32038440#11"/>
    </vehicle>

    <vehicle id="vehicle_264" type="DEFAULT_VEHTYPE" depart="556.50" departSpeed="5.00" arrival="588.70">
        <route edges="-319929498#3 32038440#11"/>
    </vehicle>

    <vehicle id="vehicle_265" type="DEFAULT_VEHTYPE" depart="558.60" departSpeed="5.00" arrival="591.10">
        <route edges="-319929498#3 32038440#11"/>
    </vehicle>

    <vehicle id="vehicle_266" type="DEFAULT_VEHTYPE" depart="560.70" departSpeed="5.00" arrival="591.70">
        <route edges="-319929498#3 -319929498#2"/>
    </vehicle>

    <vehicle id="vehicle_267" type="DEFAULT_VEHTYPE" depart="562.80" departSpeed="5.00" arrival="595.40">
        <route edges="-319929498#3 32038440#11"/>
    </vehicle>

    <vehicle id="vehicle_268" type="DEFAULT_VEHTYPE" depart="564.90" departSpeed="5.00" arrival="597.30">
        <route edges="-319929498#3 32038440#11"/>
    </vehicle>

    <vehicle id="vehicle_269" type="DEFAULT_VEHTYPE" depart="567.00" departSpeed="5.00" arrival="599.00">
        <route edges="-319929498#3 32038440#11"/>
    </vehicle>

    <vehicle id="vehicle_270" type="DEFAULT_VEHTYPE" depart="569.10" departSpeed="5.00" arrival="601.20">
        <route edges="-319929498#3 32038440#11"/>
    </vehicle>

    <vehicle id="vehicle_271" type="DEFAULT_VEHTYPE" depart="571.20" departSpeed="5.00" arrival="604.40">
        <route edges="-319929498#3 32038440#11"/>
    </vehicle>

    <vehicle id="vehicle_272" type="DEFAULT_VEHTYPE" depart="573.30" departSpeed="5.00" arrival="606.20">
        <route edges="-319929498#3 32038440#11"/>
    </vehicle>

    <vehicle id="vehicle_273" type="DEFAULT_VEHTYPE" depart="575.40" departSpeed="5.00" arrival="606.20">
        <route edges="-319929498#3 -319929498#2"/>
    </vehicle>

    <vehicle id="vehicle_274" type="DEFAULT_VEHTYPE" depart="577.50" departSpeed="5.00" arrival="608.80">
        <route edges="-319929498#3 -319929498#2"/>
    </vehicle>

    <vehicle id="vehicle_275" type="DEFAULT_VEHTYPE" depart="579.60" departSpeed="5.00" arrival="610.30">
        <route edges="-319929498#3 -319929498#2"/>
    </vehicle>

    <vehicle id="vehicle_276" type="DEFAULT_VEHTYPE" depart="581.70" departSpeed="5.00" arrival="612.00">
        <route edges="-319929498#3 -319929498#2"/>
    </vehicle>

    <vehicle id="vehicle_277" type="DEFAULT_VEHTYPE" depart="583.80" departSpeed="5.00" arrival="612.20">
        <route edges="-319929498#3 32038440#11"/>
    </vehicle>

    <vehicle id="vehicle_278" type="DEFAULT_VEHTYPE" depart="585.90" departSpeed="5.00" arrival="616.10">
        <route edges="-319929498#3 32038440#11"/>
    </vehicle>

    <vehicle id="vehicle_279" type="DEFAULT_VEHTYPE" depart="588.00" departSpeed="5.00" arrival="617.10">
        <route edges="-319929498#3 -319929498#2"/>
    </vehicle>

    <vehicle id="vehicle_280" type="DEFAULT_VEHTYPE" depart="590.10" departSpeed="5.00" arrival="618.60">
        <route edges="-319929498#3 -319929498#2"/>
    </vehicle>

    <vehicle id="vehicle_281" type="DEFAULT_VEHTYPE" depart="592.20" departSpeed="5.00" arrival="620.00">
        <route edges="-319929498#3 -319929498#2"/>
    </vehicle>

    <vehicle id="vehicle_282" type="DEFAULT_VEHTYPE" depart="594.30" departSpeed="5.00" arrival="621.80">
        <route edges="-319929498#3 -319929498#2"/>
    </vehicle>

    <vehicle id="vehicle_283" type="DEFAULT_VEHTYPE" depart="596.40" departSpeed="5.00" arrival="623.30">
        <route edges="-319929498#3 -319929498#2"/>
    </vehicle>

    <vehicle id="vehicle_285" type="DEFAULT_VEHTYPE" depart="600.60" departSpeed="5.00" arrival="631.30">
        <route edges="-319929498#3 -319929498#2"/>
    </vehicle>

    <vehicle id="vehicle_286" type="DEFAULT_VEHTYPE" depart="602.70" departSpeed="5.00" arrival="633.10">
        <route edges="-319929498#3 -319929498#2"/>
    </vehicle>

    <vehicle id="vehicle_284" type="DEFAULT_VEHTYPE" depart="598.50" departSpeed="5.00" arrival="633.50">
        <route edges="-319929498#3 32038440#11"/>
    </vehicle>

    <vehicle id="vehicle_287" type="DEFAULT_VEHTYPE" depart="604.80" departSpeed="5.00" arrival="635.40">
        <route edges="-319929498#3 -319929498#2"/>
    </vehicle>

    <vehicle id="vehicle_288" type="DEFAULT_VEHTYPE" depart="606.90" departSpeed="5.00" arrival="636.70">
        <route edges="-319929498#3 32038440#11"/>
    </vehicle>

    <vehicle id="vehicle_289" type="DEFAULT_VEHTYPE" depart="609.00" departSpeed="5.00" arrival="638.50">
        <route edges="-319929498#3 32038440#11"/>
    </vehicle>

    <vehicle id="vehicle_290" type="DEFAULT_VEHTYPE" depart="611.10" departSpeed="5.00" arrival="642.10">
        <route edges="-319929498#3 32038440#11"/>
    </vehicle>

    <vehicle id="vehicle_291" type="DEFAULT_VEHTYPE" depart="613.20" departSpeed="5.00" arrival="643.00">
        <route edges="-319929498#3 -319929498#2"/>
    </vehicle>

    <vehicle id="vehicle_292" type="DEFAULT_VEHTYPE" depart="615.30" departSpeed="5.00" arrival="644.40">
        <route edges="-319929498#3 -319929498#2"/>
    </vehicle>

    <vehicle id="vehicle_293" type="DEFAULT_VEHTYPE" depart="617.40" departSpeed="5.00" arrival="646.20">
        <route edges="-319929498#3 32038440#11"/>
    </vehicle>

    <vehicle id="vehicle_294" type="DEFAULT_VEHTYPE" depart="619.50" departSpeed="5.00" arrival="647.70">
        <route edges="-319929498#3 -319929498#2"/>
    </vehicle>

    <vehicle id="vehicle_295" type="DEFAULT_VEHTYPE" depart="621.60" departSpeed="5.00" arrival="649.80">
        <route edges="-319929498#3 -319929498#2"/>
    </vehicle>

    <vehicle id="vehicle_296" type="DEFAULT_VEHTYPE" depart="623.70" departSpeed="5.00" arrival="651.90">
        <route edges="-319929498#3 32038440#11"/>
    </vehicle>

    <vehicle id="vehicle_297" type="DEFAULT_VEHTYPE" depart="625.80" departSpeed="5.00" arrival="655.20">
        <route edges="-319929498#3 32038440#11"/>
    </vehicle>

    <vehicle id="vehicle_298" type="DEFAULT_VEHTYPE" depart="627.90" departSpeed="5.00" arrival="656.00">
        <route edges="-319929498#3 -319929498#2"/>
    </vehicle>

    <vehicle id="vehicle_299" type="DEFAULT_VEHTYPE" depart="630.00" departSpeed="5.00" arrival="657.80">
        <route edges="-319929498#3 32038440#11"/>
    </vehicle>

</routes>
